configs/__init__.py
configs/default_config.yaml
configs/text_classification_config.yaml
configs/text_classification_config_batched.yaml
configs/text_classification_config_tfhub.yaml
examples/__init__.py
examples/autoMPG_with_preprocessing.py
examples/autoMPG_with_preprocessing_load.py
examples/mnist_example.py
examples/mnist_load_saved_example.py
examples/text_classification.py
examples/text_classification_gen_batched.py
tensorEvolution/__init__.py
tensorEvolution/evo_config.py
tensorEvolution/tensor_encoder.py
tensorEvolution/tensor_evolution.py
tensorEvolution/tensor_network.py
tensorEvolution/util.py
tensorEvolution/evolutionOperators/__init__.py
tensorEvolution/evolutionOperators/crossover.py
tensorEvolution/evolutionOperators/evaluation.py
tensorEvolution/evolutionOperators/mutation.py
tensorEvolution/evolutionOperators/selection.py
tensorEvolution/nodes/__init__.py
tensorEvolution/nodes/basic_nodes.py
tensorEvolution/nodes/conv_maxpool_nodes.py
tensorEvolution/nodes/embedding.py
tensorEvolution/nodes/global_avg_pooling.py
tensorEvolution/nodes/hub_node.py
tensorEvolution/nodes/io_nodes.py
tensorEvolution/nodes/node_utils.py
tensorEvolution/nodes/rnn_nodes.py
tensorEvolution/nodes/tensor_node.py
tensor_evolution-0.1.10.dist-info/LICENSE
tensor_evolution-0.1.10.dist-info/METADATA
tensor_evolution-0.1.10.dist-info/WHEEL
tensor_evolution-0.1.10.dist-info/top_level.txt
tensor_evolution-0.1.10.dist-info/RECORD
