Metadata-Version: 2.1
Name: tensor-evolution
Version: 0.1.10
Summary: Evolutionary algorithm for neural network structure
Home-page: https://github.com/cactusWhiskey/tensor-evolution
Author: Ricardo Rivero
Author-email: ricardo.fr.rivero@gmail.com
License: Apache-2.0
Classifier: License :: OSI Approved :: Apache Software License
Classifier: Programming Language :: Python
Classifier: Programming Language :: Python :: 3
Classifier: Programming Language :: Python :: 3.9
Classifier: Programming Language :: Python :: Implementation :: CPython
Classifier: Programming Language :: Python :: Implementation :: PyPy
Requires-Python: >=3.7.0
License-File: LICENSE
Requires-Dist: tensorflow
Requires-Dist: numpy
Requires-Dist: keras
Requires-Dist: sympy
Requires-Dist: networkx
Requires-Dist: PyYAML
Requires-Dist: matplotlib
Requires-Dist: ray
Requires-Dist: deap
